<?xml version="1.0" encoding="utf-8"?>
<edmx:Edmx Version="1.0" xmlns:edmx="http://schemas.microsoft.com/ado/2007/06/edmx" xmlns:m="http://schemas.microsoft.com/ado/2007/08/dataservices/metadata" xmlns:sap="http://www.sap.com/Protocols/SAPData">
    <edmx:DataServices m:DataServiceVersion="2.0">
        <Schema Namespace="ZSM_FIO_EDU_PRJ1_SRV" xml:lang="tr" sap:schema-version="1" xmlns="http://schemas.microsoft.com/ado/2008/09/edm">
            <EntityType Name="UserInformation" sap:content-version="1">
                <Key>
                    <PropertyRef Name="Username"/>
                </Key>
                <Property Name="Username" Type="Edm.String" Nullable="false" MaxLength="12" sap:unicode="false" sap:label="Kullanıcı adı" sap:creatable="false" sap:updatable="false" sap:sortable="false" sap:filterable="false"/>
                <Property Name="Name" Type="Edm.String" MaxLength="40" sap:unicode="false" sap:label="Adı" sap:creatable="false" sap:updatable="false" sap:sortable="false" sap:filterable="false"/>
                <Property Name="Surname" Type="Edm.String" MaxLength="40" sap:unicode="false" sap:label="Soyadı" sap:creatable="false" sap:updatable="false" sap:sortable="false" sap:filterable="false"/>
                <Property Name="Birthdate" Type="Edm.DateTime" Precision="7" sap:unicode="false" sap:label="Yaratma trh." sap:creatable="false" sap:updatable="false" sap:sortable="false" sap:filterable="false"/>
                <Property Name="Mail" Type="Edm.String" MaxLength="241" sap:unicode="false" sap:label="E-posta adresi" sap:creatable="false" sap:updatable="false" sap:sortable="false" sap:filterable="false"/>
            </EntityType>
            <EntityContainer Name="ZSM_FIO_EDU_PRJ1_SRV_Entities" m:IsDefaultEntityContainer="true" sap:supported-formats="atom json xlsx">
                <EntitySet Name="UserInformationSet" EntityType="ZSM_FIO_EDU_PRJ1_SRV.UserInformation" sap:creatable="false" sap:updatable="false" sap:deletable="false" sap:pageable="false" sap:content-version="1"/>
            </EntityContainer>
            <atom:link rel="self" href="http://portal.itelligence.com.tr:1020/sap/opu/odata/sap/ZSM_FIO_EDU_PRJ1_SRV/$metadata" xmlns:atom="http://www.w3.org/2005/Atom"/>
            <atom:link rel="latest-version" href="http://portal.itelligence.com.tr:1020/sap/opu/odata/sap/ZSM_FIO_EDU_PRJ1_SRV/$metadata" xmlns:atom="http://www.w3.org/2005/Atom"/>
        </Schema>
    </edmx:DataServices>
</edmx:Edmx>